saucenao_api/__init__.py
saucenao_api/containers.py
saucenao_api/errors.py
saucenao_api/params.py
saucenao_api/saucenao_api.py
saucenao_api-2.4.0.dist-info/LICENSE
saucenao_api-2.4.0.dist-info/METADATA
saucenao_api-2.4.0.dist-info/WHEEL
saucenao_api-2.4.0.dist-info/top_level.txt
saucenao_api-2.4.0.dist-info/RECORD
