Metadata-Version: 2.1
Name: saucenao_api
Version: 2.4.0
Summary: Wrapper for SauceNAO JSON API
Home-page: https://github.com/nomnoms12/saucenao_api/
Author: nomnoms12
Author-email: alexander.ign0918@gmail.com
License: UNKNOWN
Project-URL: Bug Reports, https://github.com/nomnoms12/saucenao_api/issues/
Project-URL: Source, https://github.com/nomnoms12/saucenao_api/
Platform: UNKNOWN
Classifier: Programming Language :: Python :: 3.6
Classifier: Programming Language :: Python :: 3.7
Classifier: Programming Language :: Python :: 3.8
Classifier: License :: OSI Approved :: GNU General Public License v3 (GPLv3)
Classifier: Operating System :: OS Independent
Requires-Python: >= 3.6
Provides-Extra: test
